lib/__init__.py
lib/__main__.py
lib/bot_content/__init__.py
lib/bot_settings/__init__.py
lib/redis_connection/__init__.py
sxtg/__init__.py
sxtg/__main__.py
sxtg/bot_content/__init__.py
sxtg/bot_settings/__init__.py
sxtg/redis_connection/__init__.py
sxtg_lib-0.1.2.dist-info/METADATA
sxtg_lib-0.1.2.dist-info/WHEEL
sxtg_lib-0.1.2.dist-info/top_level.txt
sxtg_lib-0.1.2.dist-info/RECORD
