Metadata-Version: 2.1
Name: sxtg-lib
Version: 0.1.2
Summary: Утилита для работы с Telegram ботом
Home-page: https://github.com/твой-репозиторий
Author: Igor
Author-email: epicprod@mail.com
Classifier: Programming Language :: Python :: 3
Classifier: License :: OSI Approved :: MIT License
Classifier: Operating System :: OS Independent
Requires-Python: >=3.11
